<text xmlns="http://www.tei-c.org/ns/1.0" xml:id="text"><body><div><pb facs="#f154"/>
<ab>
<lb/>&lt;foreign xml:lang=“la”&gt;est cum angelo in bethel vel bethleem quasi tau-
<lb/>rus in mense Aprilis. Qui in hoc signo nas-
<lb/>citur. gratiam habebit. &amp; vim in omnem bestiam
<lb/>nisi in uxorem.
<lb/>Signum Geminis dicitur quia Adam &amp;
<lb/>Eva de uno corpore plasmati fuerunt in mense
<lb/>Maii cui Geminis conceditur. In hoc signo qui
<lb/>nascitur. Pauper &amp; debilis erit. vivet in gemitu.
<lb/>Signum Cancri dicitur quia Job cancer fuit
<lb/>de filio dei in mense Junii cui Cancer additur.
<lb/>Qui in hoc signo nascitur pauper &amp; debilis erit.
<lb/>gratiam habebit &amp; gloriam paradisi possi debit.
<lb/>Signum leonis est signum Danielis quia fuit
<lb/>in lacum missus. Qui nascitur in illo signo
<lb/>andax erit &amp; latro.
<lb/>Signum virginis dicitur quia Sancta Ma-
<lb/>ria mater dei assumpta fuit in celum in
<lb/>mense Augusti qui tenet signum Virginis.
<lb/>Qui in hoc signo nascitur sapiens &amp; iocandus
<lb/>erit. sine culpa terminetur.
<lb/>Signum libre dicitur quia Judas Sca-
<lb/>rioth fecit cum Judeis ut Jhesu dei filius&lt;/foreign&gt;
<lb/>
</ab>

</div></body></text>