<text xmlns="http://www.tei-c.org/ns/1.0" xml:id="text"><body><div><pb facs="#f152"/>
<ab>
<lb/>is a signe of Water heldynge. that signe is 
<lb/>stedfast hoot and moist. Sangweynn of that kynde
<lb/>of that eyre. that signe of that tyme is good 
<lb/>to sette. &amp; to ympe trees. and to ask dette. &amp; to lete
<lb/>blood. and forto make fundementes of a trewe 
<lb/>stondynge castel. and of housynge of gret costa- 
<lb/>ges. that every man coveytith to be wel duryng
<lb/>It is forto eschue to travayle. either forto go by 
<lb/>the sees and forto hele syke men. &amp; forto take eny 
<lb/>medicyne.
<lb/>
<lb/><head>Piscis coold &amp; moist.</head>
<lb/>
<lb/>Whan the mone is in piscibus. that is a signe
<lb/>of fysshe &amp; is coolde &amp; moist. fleumatyke of kynde
<lb/>of that Water. tyme is good forto bygge &amp;
<lb/>forto selle. &amp; forto chalenge. forto rowen. &amp;
<lb/>forto sende lettres &amp; messangers. &amp; forto bygghe. hou-
<lb/>synge. forto sette trees. and forto take medycyne.
<lb/>and also forto entrete of pees &amp; love. and of
<lb/>accorde. In that signe it is to eschue forto mete
<lb/>with thyn enemyes or with hostes of kynges.
<lb/>
</ab>

</div></body></text>